redis_websocket_api/__init__.py
redis_websocket_api/__main__.py
redis_websocket_api/exceptions.py
redis_websocket_api/geo_protocol.py
redis_websocket_api/handler.py
redis_websocket_api/protocol.py
redis_websocket_api/server.py
redis_websocket_api-0.4.4.dist-info/LICENSE
redis_websocket_api-0.4.4.dist-info/METADATA
redis_websocket_api-0.4.4.dist-info/WHEEL
redis_websocket_api-0.4.4.dist-info/top_level.txt
redis_websocket_api-0.4.4.dist-info/RECORD
