Metadata-Version: 2.1
Name: redis-websocket-api
Version: 0.4.4
Summary: Redis-over-WebSocket API on top of websockets and aioredis
Home-page: https://github.com/geops/redis-websocket-api
Author: Milan Oberkirch | geOps
Author-email: milan.oberkirch@geops.de
License: MIT
Keywords: tralis websocket websockets aioredis redis
Classifier: Programming Language :: Python :: 3
Classifier: License :: OSI Approved :: MIT License
Classifier: Operating System :: POSIX
Classifier: Environment :: Web Environment
Classifier: Framework :: AsyncIO
Classifier: Intended Audience :: Developers
Classifier: Topic :: Internet :: WWW/HTTP :: HTTP Servers
Classifier: Topic :: Scientific/Engineering :: GIS
Requires-Python: >=3.7
License-File: LICENSE
Requires-Dist: aioredis
Requires-Dist: websockets
Requires-Dist: hiredis
Provides-Extra: geo
Requires-Dist: pyproj (>=2.2.0) ; extra == 'geo'
Provides-Extra: testing
Requires-Dist: pytest ; extra == 'testing'
